hpyhex/__init__.py
hpyhex/benchmark.py
hpyhex/game.py
hpyhex/hex.py
hpyhex-0.2.0.1.dist-info/licenses/LICENSE
hpyhex-0.2.0.1.dist-info/METADATA
hpyhex-0.2.0.1.dist-info/WHEEL
hpyhex-0.2.0.1.dist-info/top_level.txt
hpyhex-0.2.0.1.dist-info/RECORD
