Metadata-Version: 2.4
Name: hpyhex
Version: 0.2.0.1
Summary: Simplified implementations of the HappyHex game components and hexagonal system in Python.
Author-email: William Wu <williamwutq@gmail.com>
License-Expression: MIT
License-File: LICENSE
Dynamic: license-file
